{"cameraMode":{"drawMode":0,"name":"Shaded","section":"Shading Mode"},"sceneLighting":true,"audioPlay":false,"sceneViewState":{"m_AlwaysRefresh":false,"showFog":true,"showSkybox":true,"showFlares":true,"showImageEffects":true,"showParticleSystems":true,"showVisualEffectGraphs":true,"m_FxEnabled":true},"in2DMode":false,"pivot":{"x":36.094932556152347,"y":-98.69798278808594,"z":227.7785186767578},"rotation":{"x":0.19195254147052766,"y":0.10470748692750931,"z":-0.020625637844204904,"w":0.9756682515144348},"size":139.99038696289063,"orthographic":false}