{"cameraMode":{"drawMode":0,"name":"Shaded","section":"Shading Mode"},"sceneLighting":true,"audioPlay":false,"sceneViewState":{"m_AlwaysRefresh":false,"showFog":true,"showSkybox":true,"showFlares":true,"showImageEffects":true,"showParticleSystems":true,"showVisualEffectGraphs":true,"m_FxEnabled":true},"in2DMode":false,"pivot":{"x":32.51883316040039,"y":14.043181419372559,"z":306.80072021484377},"rotation":{"x":0.013408091850578785,"y":0.08735613524913788,"z":-0.001676140702329576,"w":0.9956644177436829},"size":106.67462158203125,"orthographic":false}